mpremote2/__init__.py
mpremote2/__main__.py
mpremote2/commands.py
mpremote2/console.py
mpremote2/main.py
mpremote2/mip.py
mpremote2/repl.py
mpremote2/transport.py
mpremote2/transport_serial.py
mpremote2-1.22.1.dist-info/METADATA
mpremote2-1.22.1.dist-info/WHEEL
mpremote2-1.22.1.dist-info/top_level.txt
mpremote2-1.22.1.dist-info/RECORD
