Metadata-Version: 2.1
Name: mpremote2
Version: 1.22.1
Summary: Tool for interacting remotely with MicroPython devices; includes improved serialport handling
Author: Chris Drake
Author-email: support@micropython.org
License: MIT
Project-URL: Homepage, https://github.com/micropython/micropython
Keywords: hardware,micropython
Classifier: Intended Audience :: Developers
Classifier: License :: OSI Approved :: MIT License
Classifier: Operating System :: OS Independent
Classifier: Programming Language :: Python :: 3
Classifier: Topic :: Software Development :: Embedded Systems
Classifier: Topic :: System :: Hardware
Requires-Python: >=3.4
Requires-Dist: importlib-metadata >=1.4
Requires-Dist: pyserial >=3.3
